twx/__init__.py
twx/botapi/__init__.py
twx/botapi/botapi.py
twx.botapi-3.6.1.dist-info/LICENSE.txt
twx.botapi-3.6.1.dist-info/METADATA
twx.botapi-3.6.1.dist-info/RECORD
twx.botapi-3.6.1.dist-info/WHEEL
twx.botapi-3.6.1.dist-info/top_level.txt
