Metadata-Version: 2.1
Name: twx.botapi
Version: 3.6.1
Summary: Unofficial Telegram Bot API Library and Client
Home-page: https://github.com/datamachine/twx.botapi
Author: Vince Castellano, Phillip Lopo
Author-email: surye80@gmail.com, philliplopo@gmail.com
License: UNKNOWN
Download-URL: https://github.com/datamachine/twx.botapi/archive/3.6.1.zip
Keywords: datamachine,telex,telegram,bot,api,rpc,twx,chat
Platform: Linux
Platform: FreeBSD
Platform: BSD
Platform: Unix
Platform: Mac
Platform: OS X
Platform: Windows
Classifier: Development Status :: 5 - Production/Stable
Classifier: Intended Audience :: Developers
Classifier: License :: OSI Approved :: MIT License
Classifier: Operating System :: OS Independent
Classifier: Programming Language :: Python :: 2.7
Classifier: Programming Language :: Python :: 3.0
Classifier: Programming Language :: Python :: 3.1
Classifier: Programming Language :: Python :: 3.2
Classifier: Programming Language :: Python :: 3.3
Classifier: Programming Language :: Python :: 3.4
Classifier: Programming Language :: Python :: 3.5
Classifier: Programming Language :: Python :: 3.6
Classifier: Topic :: Communications :: Chat
Classifier: Topic :: Communications :: File Sharing
Classifier: Topic :: Software Development :: Libraries
Classifier: Topic :: Software Development :: Libraries :: Python Modules
Requires-Dist: requests
Requires-Dist: attrs
